PGLW/__init__.py
PGLW/version.py
PGLW/components/__init__.py
PGLW/components/airfoil.py
PGLW/components/bladecap.py
PGLW/components/blademesher.py
PGLW/components/bladeroot.py
PGLW/components/bladetip.py
PGLW/components/coonsblade.py
PGLW/components/erosion.py
PGLW/components/loftedblade.py
PGLW/components/nacelle.py
PGLW/components/pointwiser.py
PGLW/components/surfaceslicer.py
PGLW/components/vgmesher.py
PGLW/components/vgunit.py
PGLW/examples/__init__.py
PGLW/examples/blademesher_1b_example.py
PGLW/examples/blademesher_1b_flap_example.py
PGLW/examples/blademesher_example.py
PGLW/examples/blademesher_example_c2d.py
PGLW/examples/blademesher_nacelle_example.py
PGLW/examples/blademesher_windio.py
PGLW/examples/bladeroot_example.py
PGLW/examples/coons_extrusion_example.py
PGLW/examples/coonsblade_example.py
PGLW/examples/coonstip_example.py
PGLW/examples/loftedblade_example.py
PGLW/examples/surfaceslicer_example.py
PGLW/examples/vg_example.py
PGLW/examples/data/DTU_10MW_RWT_blade_axis_prebend.dat
PGLW/examples/data/DTU_10MW_RWT_blade_axis_straight_fine.dat
PGLW/examples/data/cylinder.dat
PGLW/examples/data/ffaw3241.dat
PGLW/examples/data/ffaw3301.dat
PGLW/examples/data/ffaw3360.dat
PGLW/examples/data/ffaw3480.dat
PGLW/examples/data/tc72.dat
PGLW/main/__init__.py
PGLW/main/airfoil.py
PGLW/main/bezier.py
PGLW/main/bezierpatch.py
PGLW/main/bladecap.py
PGLW/main/blademesher.py
PGLW/main/bladeroot.py
PGLW/main/bladetip.py
PGLW/main/boxmesh.py
PGLW/main/coons.py
PGLW/main/coons_extrusion.py
PGLW/main/coonsblade.py
PGLW/main/cubicspline.py
PGLW/main/curve.py
PGLW/main/distfunc.py
PGLW/main/domain.py
PGLW/main/erosion.py
PGLW/main/geom_tools.py
PGLW/main/hawc2_planform.py
PGLW/main/loftedblade.py
PGLW/main/nacelle.py
PGLW/main/naturalcubicspline.py
PGLW/main/pglcomponent.py
PGLW/main/pglmesher.py
PGLW/main/planform.py
PGLW/main/pointwiser.py
PGLW/main/surfaceslicer.py
PGLW/main/vgmesher.py
PGLW/main/vgunit.py
PGLW/main/windio.py
PGLW/test/__init__.py
PGLW/test/main_h2.htc
pglw-1.3.1.dist-info/LICENSE
pglw-1.3.1.dist-info/METADATA
pglw-1.3.1.dist-info/WHEEL
pglw-1.3.1.dist-info/top_level.txt
pglw-1.3.1.dist-info/RECORD
