Metadata-Version: 2.2
Name: PGLW
Version: 1.3.1
Summary: Parametric Geometry Library for Wind Turbines
Author-email: "Department of Wind and Energy Systems, DTU" <frza@dtu.dk>
Maintainer-email: Frederik Zahle <frza@dtu.dk>
Project-URL: Homepage, https://gitlab.windenergy.dtu.dk/frza/PGL
Project-URL: Bug Tracker, https://gitlab.windenergy.dtu.dk/frza/PGL/-/issues
Classifier: Programming Language :: Python :: 3
Classifier: Operating System :: OS Independent
Requires-Python: >=3.8
License-File: LICENSE
Requires-Dist: numpy
Requires-Dist: scipy
Requires-Dist: black==24.8.0
Requires-Dist: isort==5.6.4
Requires-Dist: flake8==5.0.4
Requires-Dist: ruamel.yaml
Provides-Extra: test
Requires-Dist: coverage; extra == "test"
Provides-Extra: docs
Requires-Dist: sphinx; extra == "docs"
Requires-Dist: numpydoc; extra == "docs"
Requires-Dist: nbsphinx; extra == "docs"
Requires-Dist: sphinx_rtd_theme; extra == "docs"
Requires-Dist: sphinxcontrib-napoleon; extra == "docs"
